{
  "product_name_ru": "складная миска для питомца",
  "core_label_ru": "складная миска для питомца",
  "scenario_ru": "для кухни",
  "category_ru": "宠物",
  "selected_title_ru": "складная миска для питомца",
  "title_candidates_ru": [
    "складная миска для питомца",
    "складная миска для питомца для кухни",
    "складная миска для питомца для 宠物",
    "складная миска для питомца - 轻便、可折叠、易清洗，适合宠物主人日常及出行使用"
  ],
  "keyword_hints_ru": [
    "складная миска для питомца",
    "для кухни",
    "宠物",
    "硅胶折叠宠物食碗"
  ]
}
