{
  "slug": "item-4-9d1f91aa",
  "compared_at": "2026-03-26T08:07:06.196Z",
  "candidate_count": 3,
  "selected_offer_source_url": "https://detail.1688.com/offer/979663612935.html",
  "shortlist": [
    {
      "rank": 1,
      "source_url": "https://detail.1688.com/offer/979663612935.html",
      "shop_name": "1688台州日百选品中心",
      "offer_title": "可伸缩桌面收纳盒（带分隔）",
      "price": 20.87,
      "min_order_qty": 1688
    },
    {
      "rank": 2,
      "source_url": "https://detail.1688.com/offer/1017232524953.html",
      "shop_name": "台州橙言家居用品有限公司",
      "offer_title": "可伸缩桌面收纳盒（带分隔）",
      "price": 15.8,
      "min_order_qty": 10
    },
    {
      "rank": 3,
      "source_url": "https://detail.1688.com/offer/1014689715399.html",
      "shop_name": "台州小乘塑业有限公司",
      "offer_title": "可伸缩桌面收纳盒（带分隔）",
      "price": 15.8,
      "min_order_qty": 99996
    }
  ],
  "search_attempts": [
    {
      "keyword": "可伸缩桌面收纳盒 带分隔",
      "page_type": "search",
      "card_count": 15,
      "offer_link_count": 18,
      "title": "可伸缩桌面收纳盒 带分隔_可伸缩桌面收纳盒 带分隔批发_可伸缩桌面收纳盒 带分隔供应_阿里巴巴",
      "body_snippet": "搜 索 桌面 抽屉 收纳盒 大号 桌面 抽屉 收纳 收纳盒 布 桌面 增高器架 分隔收纳收纳盒 分隔收纳盒 收纳盒 无盖 桌面 书本 收纳 桌面 绘本架 热门搜索 春季韩系上衣 卡洛驰洞洞鞋 今年流行漂亮的女装 女童超好看韩系上衣 以图搜款 支持如下图搜同款比价方式 1. 点击从本地上传图片 2. ctrl + v 粘"
    },
    {
      "keyword": "可伸缩桌面收纳盒带分隔",
      "page_type": "search",
      "card_count": 15,
      "offer_link_count": 18,
      "title": "可伸缩桌面收纳盒带分隔_可伸缩桌面收纳盒带分隔批发_可伸缩桌面收纳盒带分隔供应_阿里巴巴",
      "body_snippet": "搜 索 桌面 抽屉 收纳盒 大号 桌面 抽屉 收纳 收纳盒 布 桌面 增高器架 分隔收纳收纳盒 分隔收纳盒 收纳盒 无盖 桌面 书本 收纳 桌面 绘本架 热门搜索 春季新款上衣 春季韩系上衣 女童超好看韩系上衣 鞋柜收纳柜一体靠墙 以图搜款 支持如下图搜同款比价方式 1. 点击从本地上传图片 2. ctrl + v 粘"
    },
    {
      "keyword": "可伸缩桌面收纳盒 带分隔 1688",
      "page_type": "search",
      "card_count": 15,
      "offer_link_count": 5,
      "title": "可伸缩桌面收纳盒 带分隔 1688_可伸缩桌面收纳盒 带分隔 1688批发_可伸缩桌面收纳盒 带分隔 1688供应_阿里巴巴",
      "body_snippet": "搜 索 桌面 抽屉 收纳盒 大号 桌面 抽屉 收纳 收纳盒 布 桌面 增高器架 分隔收纳收纳盒 分隔收纳盒 收纳盒 无盖 桌面 书本 收纳 桌面 绘本架 热门搜索 收纳箱收纳家用 海岛拍照绝美裙 夏日女装 妈妈款春装外套 以图搜款 支持如下图搜同款比价方式 1. 点击从本地上传图片 2. ctrl + v 粘贴图片或图"
    }
  ],
  "notes": []
}
