{
  "_meta": {
    "version": 2,
    "description": "动态关键词池 — 支持手动添加和AI自动扩展",
    "total_categories": 19,
    "last_expanded_at": "2026-03-31T12:18:30.389Z"
  },
  "categories": {
    "auto": {
      "label": "汽车用品",
      "enabled": true,
      "target_users": "Car owners",
      "keywords": [
        "车载缝隙收纳盒",
        "后备箱收纳网兜",
        "车载手机支架 出风口",
        "汽车遮阳挡 前挡",
        "车载垃圾桶 折叠",
        "方向盘手机支架",
        "汽车后座挂钩",
        "车载香薰 出风口夹",
        "汽车座椅背收纳袋",
        "车载纸巾盒",
        "汽车钥匙扣",
        "车载充电器支架",
        "汽车安全带护肩套",
        "车载眼镜夹 遮阳板",
        "汽车后视镜小圆镜 盲区",
        "汽车中控台储物盒",
        "车载雨伞挂钩 后座",
        "汽车座椅缝隙填充条",
        "车载行车记录仪支架",
        "汽车侧窗遮阳帘 折叠",
        "汽车车门把手保护套 硅胶",
        "车载手套箱收纳袋"
      ]
    },
    "pet": {
      "label": "宠物用品",
      "enabled": true,
      "target_users": "Pet owners",
      "keywords": [
        "宠物粘毛器",
        "宠物饮水器 自动循环",
        "猫砂铲 漏砂",
        "宠物牵引绳 伸缩",
        "猫抓板 瓦楞纸",
        "宠物慢食碗",
        "狗狗拾便袋",
        "宠物外出水壶",
        "猫玩具 逗猫棒",
        "宠物梳毛手套",
        "狗狗雨衣",
        "宠物车载安全座椅",
        "猫咪项圈 铃铛",
        "宠物指甲剪 磨甲",
        "狗狗口套 防咬",
        "宠物硅胶折叠碗",
        "猫咪自嗨玩具 电动",
        "宠物牙刷 指套",
        "猫粮密封储粮桶",
        "宠物除臭喷雾",
        "狗狗训练零食袋 腰包",
        "宠物驱虫滴剂 跳蚤"
      ]
    },
    "kitchen": {
      "label": "厨房用品",
      "enabled": true,
      "target_users": "Urban families",
      "keywords": [
        "冰箱收纳盒",
        "厨房调料架 旋转",
        "锅盖架 台面",
        "厨房水槽沥水篮",
        "硅胶保鲜盖 万能",
        "厨房刀架 壁挂磁吸",
        "厨房垃圾袋挂架",
        "食品封口夹 密封",
        "厨房计时器 磁吸",
        "硅胶锅垫 隔热",
        "不锈钢夹子 食品",
        "厨房置物架 多层",
        "硅胶刮刀 烘焙耐高温",
        "厨房漏斗 折叠硅胶",
        "磁吸冰箱挂钩 厨房",
        "蔬菜清洗盆 沥水双层",
        "厨房纸巾架 壁挂免打孔",
        "硅胶蒸笼垫 圆形",
        "不锈钢开瓶器 多功能",
        "厨房油壶 防漏玻璃",
        "保鲜膜切割器 壁挂",
        "厨房称重秤 迷你电子"
      ]
    },
    "home_storage": {
      "label": "家居收纳",
      "enabled": true,
      "target_users": "Urban families",
      "keywords": [
        "抽屉分隔盒",
        "浴室收纳架 免打孔",
        "衣柜收纳分层隔板",
        "鞋柜收纳鞋架 双层",
        "墙壁挂钩 免打孔",
        "衣物压缩袋 真空",
        "桌面收纳盒 化妆品",
        "门后挂钩 免钉",
        "透明收纳箱 可叠放",
        "衣橱分格收纳",
        "首饰收纳盒 多层",
        "遥控器收纳架",
        "厨房刀叉收纳盒 带盖",
        "冰箱侧面挂架 磁吸",
        "床头手机充电收纳袋",
        "儿童玩具收纳桶 折叠",
        "桌面电线收纳盒 理线",
        "厨房调料瓶收纳架 转盘",
        "文件收纳盒 桌面 带盖",
        "洗漱台收纳杯 牙刷架",
        "衣物分类收纳袋 旅行",
        "壁挂钥匙收纳盒 门口"
      ]
    },
    "desk": {
      "label": "办公桌面",
      "enabled": true,
      "target_users": "Office workers",
      "keywords": [
        "桌面理线器",
        "显示器增高架",
        "笔记本电脑支架 折叠",
        "桌面文件收纳架",
        "手机支架 桌面 可调节",
        "鼠标垫 超大",
        "桌面小台灯 护眼",
        "笔筒 创意",
        "键盘腕托 记忆棉",
        "耳机支架 桌面 铝合金",
        "亚克力桌面收纳盒 多格",
        "桌面磁性小白板",
        "鼠标腕托 硅胶",
        "无线充电支架 桌面 多功能",
        "桌面挂钩 侧面收纳",
        "办公室香薰机 小型 USB",
        "桌面垃圾桶 带盖 迷你",
        "名片盒 桌面 商务"
      ]
    },
    "travel": {
      "label": "旅行户外",
      "enabled": true,
      "target_users": "Travelers",
      "keywords": [
        "旅行鞋袋 收纳",
        "旅行分装瓶 套装",
        "行李箱收纳袋 压缩",
        "折叠水杯 硅胶",
        "便携式衣架 折叠",
        "旅行收纳包 数码",
        "护照包 多功能",
        "行李牌 创意",
        "旅行洗漱包 防水",
        "颈枕 记忆棉 U型",
        "旅行分装瓶 喷雾",
        "行李束带 打包带",
        "旅行眼罩 耳塞套装",
        "折叠雨衣 便携",
        "旅行挂锁 密码锁",
        "鞋套 防水 便携",
        "旅行药盒 分装",
        "充气脚踏枕 飞机"
      ]
    },
    "cleaning": {
      "label": "清洁工具",
      "enabled": true,
      "target_users": "Homeowners",
      "keywords": [
        "窗户清洁刮水器",
        "缝隙清洁刷",
        "马桶刷 硅胶 壁挂",
        "拖把挤水桶 旋转",
        "除霉啫喱 防霉",
        "地漏过滤器 硅胶",
        "纱窗清洁刷",
        "鞋刷 多功能",
        "洗碗布 不沾油 纤维",
        "水槽过滤网 硅胶 防堵",
        "魔术海绵 去污 纳米",
        "卫生间角落清洁刷 长柄",
        "滚筒粘毛器 可撕式",
        "厨房油烟机过滤棉",
        "硅胶刮水器 浴室墙面",
        "桌面扫把套装 迷你",
        "洗衣机槽清洗剂 泡腾片",
        "暖气片清洁刷 长柄细毛"
      ]
    },
    "gadgets": {
      "label": "生活小工具",
      "enabled": true,
      "target_users": "Everyone",
      "keywords": [
        "迷你封口机 便携",
        "自动感应垃圾桶",
        "LED灯带 遥控",
        "USB小风扇 桌面",
        "懒人手机支架 床头",
        "电动指甲刀 婴儿",
        "自动搅拌杯 磁力",
        "温湿度计 电子",
        "夜灯 人体感应",
        "开瓶器 创意",
        "硅胶折叠水杯 便携",
        "磁吸手机壳 多功能",
        "电动牙刷 声波 USB充电",
        "计时器 厨房 磁吸",
        "折叠剪刀 便携 多功能",
        "硅胶冰格 带盖 食品级",
        "指尖陀螺 解压玩具",
        "电子打火机 USB充电",
        "卷发棒 迷你 便携",
        "挂钩 强力 无痕 粘贴"
      ]
    },
    "baby": {
      "label": "母婴用品",
      "enabled": true,
      "target_users": "New parents",
      "keywords": [
        "婴儿防撞角 硅胶",
        "儿童餐盘 硅胶吸盘",
        "婴儿指甲剪套装",
        "奶瓶沥水架",
        "婴儿安全锁 柜门",
        "儿童牙刷 U型",
        "防走失手环",
        "婴儿围嘴 硅胶",
        "婴儿硅胶牙胶 磨牙棒",
        "新生儿包被 纯棉",
        "婴儿洗澡网兜 浴盆支架",
        "儿童防夹手门缝保护条",
        "婴儿辅食研磨碗套装",
        "宝宝学饮杯 硅胶吸管",
        "婴儿鼻腔清洁器 吸鼻器",
        "儿童安全插座保护盖",
        "婴儿睡袋 防踢被",
        "宝宝手指套牙刷 硅胶"
      ]
    },
    "fitness": {
      "label": "运动健身",
      "enabled": true,
      "target_users": "Fitness enthusiasts",
      "keywords": [
        "瑜伽垫 加厚防滑",
        "筋膜球 按摩",
        "跳绳 计数",
        "握力器 可调节",
        "运动腰包 跑步",
        "弹力带 健身",
        "运动水壶 大容量",
        "护膝 运动",
        "瑜伽袜 防滑分趾",
        "健身手套 半指防滑",
        "运动毛巾 细纤维速干",
        "健腹轮 静音双轮",
        "肌效贴 运动防水",
        "运动护腕 加压缠绕",
        "跑步护踝 薄款",
        "计步器 夹式计步",
        "拉力器 弹簧胸肌",
        "冷热敷袋 运动冰敷"
      ]
    },
    "stationery": {
      "label": "文具手工",
      "enabled": true,
      "target_users": "Students/crafters",
      "keywords": [
        "彩色胶带 和纸胶带",
        "自粘便签纸 创意",
        "手账贴纸 套装",
        "荧光笔 套装",
        "文件袋 拉链",
        "尺子 多功能",
        "水彩笔 儿童套装",
        "折叠剪刀 便携",
        "印章套装 手账",
        "彩色铅笔 油性",
        "笔袋 大容量 学生",
        "订书机 迷你 便携",
        "白板笔 可擦写",
        "胶棒 固体胶水",
        "橡皮擦 创意造型",
        "卷笔刀 电动 便携"
      ]
    },
    "clothing": {
      "label": "服装鞋帽",
      "enabled": true,
      "target_users": "Fashion consumers",
      "keywords": [
        "男士T恤 纯棉 圆领",
        "女士打底裤 加绒",
        "运动袜 男 中筒",
        "棒球帽 刺绣",
        "围巾 仿羊绒",
        "手套 触屏 保暖",
        "男士内裤 莫代尔",
        "女士内衣 无钢圈",
        "儿童连体衣",
        "男士休闲裤 弹力",
        "女士瑜伽裤",
        "拖鞋 家居 防滑",
        "雪地靴 女",
        "帆布鞋 男",
        "运动鞋 轻便 透气",
        "腰带 男士 自动扣",
        "领带 商务",
        "丝巾 女士",
        "女士卫衣 宽松 韩版",
        "运动文胸 高强度 聚拢",
        "儿童袜子 纯棉 防滑",
        "男士沙滩短裤 速干",
        "女士睡衣 丝绸质感 两件套",
        "针织毛线帽 女 秋冬",
        "保暖背心 男 加厚马甲",
        "女士雪纺衬衫 宽松",
        "男士运动紧身裤 压缩",
        "儿童羽绒服 轻薄 连帽"
      ]
    },
    "accessories": {
      "label": "配饰箱包",
      "enabled": true,
      "target_users": "Fashion consumers",
      "keywords": [
        "手表 石英 简约",
        "太阳镜 偏光",
        "手链 钛钢",
        "耳环 长款 流苏",
        "项链 锁骨链",
        "发夹 珍珠",
        "双肩包 大容量",
        "斜挎包 男 休闲",
        "化妆包 便携",
        "钱包 男 短款",
        "卡包 多卡位",
        "腰包 运动",
        "戒指 开口 可调节 女",
        "发带 丝绒 宽边",
        "胸针 复古 合金",
        "托特包 帆布 轻便",
        "钥匙扣 皮质 创意",
        "手镯 天然石 水晶",
        "发箍 宽边 塑料",
        "颈链 金属 朋克",
        "行李牌 皮革 旅行",
        "帽子 针织 毛线 女"
      ]
    },
    "electronics_light": {
      "label": "轻电子",
      "enabled": true,
      "target_users": "Tech consumers",
      "keywords": [
        "蓝牙耳机 入耳式",
        "数据线 快充 三合一",
        "充电宝 迷你",
        "手机壳 硅胶 防摔",
        "屏幕保护膜 钢化",
        "USB集线器",
        "无线鼠标 静音",
        "键盘 机械 迷你",
        "摄像头遮挡贴",
        "手机支架 懒人 桌面",
        "蓝牙音箱 迷你 防水",
        "Type-C 读卡器 多合一",
        "无线充电器 15W 薄",
        "耳机收纳盒 硬壳",
        "手机散热器 背夹",
        "磁吸手机壳 支架 MagSafe",
        "防蓝光眼镜 电脑",
        "数据线收纳夹 硅胶",
        "屏幕清洁套装 手机"
      ]
    },
    "beauty_skincare_tools": {
      "label": "美妆护肤工具",
      "enabled": true,
      "target_users": "18-45岁女性，注重日常护肤与美容仪式感的城市女性",
      "keywords": [
        "маска для лица тканевая",
        "роллер для лица нефритовый",
        "гуаша камень для лица",
        "патчи под глаза гидрогелевые",
        "скраб для лица",
        "пенка для умывания",
        "коллагеновая маска корейская",
        "массажер для лица электрический",
        "микроигольный патч для лица",
        "сыворотка для лица витамин С",
        "очищающие полоски для носа",
        "щётка для умывания лица",
        "маска альгинатная",
        "силиконовый массажер для лица",
        "косметические диски многоразовые",
        "眼部按摩仪 充电",
        "美容冰敷眼罩 硅胶",
        "洁面仪 硅胶软毛 USB",
        "黑头吸附鼻贴 撕拉式",
        "面部刮痧板 玫瑰石英",
        "蒸脸器 纳米喷雾 便携",
        "美容导入仪 超声波",
        "眼膜托 硅胶 固定",
        "磁石面膜碗 调膜棒套装",
        "睫毛卷翘器 加热烫睫毛"
      ]
    },
    "holiday_party_decor": {
      "label": "节日派对装饰",
      "enabled": true,
      "target_users": "家庭主妇、派对策划者、节日活动组织者，尤其是新年/生日场景需求旺盛",
      "keywords": [
        "гирлянда светодиодная новогодняя",
        "воздушные шары фольгированные",
        "украшения на новый год",
        "баннер с днём рождения",
        "конфетти декоративное",
        "фотозона для вечеринки",
        "свечи для торта декоративные",
        "мишура серпантин",
        "топперы для торта",
        "шарики для фотосессии",
        "флажки праздничная гирлянда",
        "наклейки декоративные для праздника",
        "декор стола на день рождения",
        "помпоны из бумаги тишью",
        "фонтан из шаров набор",
        "气球装饰套装 生日派对",
        "拉旗彩旗串 节日装饰",
        "蛋糕装饰插件 派对",
        "螺旋吊饰 天花板装饰",
        "派对眼镜 搞怪道具",
        "网红背景墙布置套装",
        "金属气球数字 生日",
        "流苏拉花 派对装饰",
        "桌飘气球夹 固定支架",
        "礼花弹彩带炮 派对"
      ]
    },
    "gardening_planting": {
      "label": "园艺种植",
      "enabled": true,
      "target_users": "有达恰（дача）的中老年家庭、阳台种植爱好者、城市园艺初学者",
      "keywords": [
        "семена цветов для дачи",
        "семена овощей томаты огурцы",
        "горшок для рассады пластиковый",
        "торфяные таблетки для рассады",
        "мини теплица для балкона",
        "кашпо подвесное декоративное",
        "поддон для цветочного горшка",
        "опрыскиватель для растений",
        "лейка комнатная маленькая",
        "дренаж для горшков керамзит",
        "удобрение для рассады жидкое",
        "набор садовых инструментов мини",
        "подставка для цветов",
        "рассадник торфяной",
        "органайзер для семян",
        "植物标签牌 防水",
        "园艺绑枝夹 软",
        "种子发芽盒 透明",
        "植物支撑杆 竹木",
        "自动浇水器 懒人",
        "花盆托盘 沥水",
        "园艺手套 防刺",
        "嫁接刀 园艺工具",
        "植物营养液 通用",
        "蜗牛药 花园防虫"
      ]
    },
    "aromatherapy_bath": {
      "label": "香薰沐浴个护",
      "enabled": true,
      "target_users": "追求生活品质的25-50岁女性，喜爱居家SPA体验及天然香氛产品",
      "keywords": [
        "бомбочки для ванны набор",
        "соль для ванны гималайская",
        "аромасвеча соевая",
        "аромадиффузор электрический",
        "эфирное масло лаванды",
        "пена для ванны натуральная",
        "скраб для тела сахарный",
        "масло для тела миндальное",
        "натуральное мыло ручной работы",
        "ароматизатор для дома тростниковый",
        "мочалка люффа натуральная",
        "набор для ухода за телом подарочный",
        "спрей для подушки расслабляющий",
        "бальзам для губ натуральный",
        "скраб для губ",
        "竹炭手工皂 洁面",
        "牛油果身体乳 保湿",
        "咖啡磨砂膏 去角质",
        "茶树精油 纯植物",
        "玫瑰果油 护肤",
        "干花香薰蜡烛 装饰",
        "沐浴花束 鲜花皂",
        "天然猪鬃沐浴刷 长柄",
        "香薰睡眠眼罩 遮光",
        "精油滚珠瓶 便携"
      ]
    },
    "board_games_puzzles": {
      "label": "桌游益智玩具",
      "enabled": true,
      "target_users": "6-14岁儿童家长、朋友聚会人群、亲子互动家庭，节假日送礼场景强",
      "keywords": [
        "настольная игра для детей",
        "пазл 1000 деталей",
        "карточная игра для компании",
        "головоломка для детей",
        "кубик Рубика",
        "деревянные пазлы 3D",
        "игра на реакцию для детей",
        "магнитный конструктор",
        "пазл антистресс для взрослых",
        "настольная игра для всей семьи",
        "карточная игра Uno аналог",
        "детское лото деревянное",
        "пазл напольный для малышей",
        "логическая игра головоломка деревянная",
        "игра мемори для детей",
        "叠叠乐 抽积木 儿童",
        "七巧板 木质 儿童益智",
        "多米诺骨牌 儿童玩具",
        "磁性钓鱼玩具 木质",
        "儿童国际象棋 折叠棋盘",
        "儿童串珠穿线 益智玩具",
        "飞行棋 折叠 儿童桌游",
        "儿童翻转棋 黑白棋",
        "数独游戏 儿童木质",
        "彩虹圆环套圈 益智玩具"
      ]
    }
  }
}