{
  "title_ru": "Кухонные весы электронные мини, Точные весы для кухни, Высокая точность 1 г, Взвешивание продуктов, выпечки, трав",
  "title_en": "Mini Electronic Kitchen Scale, High Precision 1g, Food Scale for Baking, Herbs",
  "description_ru": "Миниатюрные и точные электронные кухонные весы \"Qianque\" станут незаменимым помощником на вашей кухне. Идеально подходят для взвешивания ингредиентов при приготовлении выпечки, диетических блюд, а также для точного дозирования трав и специй. Благодаря компактному размеру и стильному дизайну весы легко поместятся в любом кухонном шкафчике.\n\nВесы обладают высокой точностью измерения до 1 грамма и широким диапазоном взвешивания, что позволяет использовать их как для мелких, так и для более крупных продуктов. Простой интерфейс с одной кнопкой управления и четкий ЖК-дисплей делают использование интуитивно понятным. Автоматическое отключение и индикация низкого заряда батареи продлевают срок службы устройства.",
  "bullet_points_ru": [
    "Высокая точность измерения до 1 грамма",
    "Компактный и стильный дизайн, экономия места",
    "Простое управление одной кнопкой и четкий ЖК-дисплей",
    "Автоматическое отключение для экономии заряда батареи",
    "Широкий диапазон взвешивания для разных продуктов"
  ],
  "ozon_category_suggestion": "Кухонные весы",
  "ozon_type_name": "Кухонные весы",
  "attributes": {
    "brand": "Qianque",
    "model": "A600",
    "color": "Белый",
    "material": "Пластик, Стекло (платформа)",
    "size": "Небольшой (примерно 15x15x2 см)",
    "weight_kg": 0.25,
    "country_of_origin": "CN",
    "vendor_code": "A600",
    "barcode": ""
  },
  "compliance": {
    "is_adult": false,
    "is_fragile": true,
    "dangerous_goods": false,
    "certificate_required": false,
    "restricted_category": false
  },
  "seo_keywords_ru": [
    "кухонные весы электронные",
    "мини весы для кухни",
    "точные весы для выпечки",
    "весы для продуктов",
    "кухонные весы 1 грамм"
  ],
  "confidence": 0.85,
  "inferred_at": "2026-04-04T03:07:10.611Z",
  "source_slug": "厨房称重秤-迷你电子-62b80393"
}
