{
  "title_ru": "Защита для ремня безопасности автомобиля с отверстиями для игрушек, съемный чехол для детей и взрослых, 2 шт.",
  "title_en": "Car Seat Belt Shoulder Pad Cover with Holes for Toys, Removable Protector for Kids and Adults, 2pcs",
  "description_ru": "Удобные и практичные защитные накладки на ремень безопасности автомобиля. Идеально подходят для семей с детьми, делают каждую поездку более комфортной и безопасной для маленьких пассажиров. Мягкий материал предотвращает натирание и дискомфорт от стандартного ремня.\n\nЧехлы легко устанавливаются и снимаются благодаря удобной конструкции. Универсальный размер подходит для большинства автомобилей. Отверстия позволяют крепить любимые игрушки или аксессуары, развлекая ребенка в дороге. Отличный подарок для автовладельцев и родителей.",
  "bullet_points_ru": [
    "Мягкая защита от натирания ремнем безопасности",
    "Универсальный размер для большинства автомобилей",
    "Отверстия для крепления игрушек и аксессуаров",
    "Легко устанавливается и снимается без инструментов",
    "Комплект из 2 штук для водителя и пассажира"
  ],
  "ozon_category_suggestion": "Автомобильные аксессуары",
  "ozon_type_name": "Аксессуары",
  "attributes": {
    "brand": "蓝雨 (Blue Rain)",
    "model": "Съемный чехол с отверстиями",
    "color": "Разные цвета (изображения)",
    "material": "Полиэстер, мягкий наполнитель",
    "size": "Универсальный",
    "weight_kg": 0.15,
    "country_of_origin": "CN",
    "vendor_code": "带孔护肩",
    "barcode": ""
  },
  "compliance": {
    "is_adult": false,
    "is_fragile": false,
    "dangerous_goods": false,
    "certificate_required": false,
    "restricted_category": false
  },
  "seo_keywords_ru": [
    "защита ремня безопасности",
    "чехол на ремень автомобиля",
    "детский аксессуар для авто",
    "накладка на ремень",
    "автомобильные аксессуары"
  ],
  "confidence": 0.75,
  "inferred_at": "2026-04-04T02:43:35.330Z",
  "source_slug": "汽车安全带护肩套-e228582f"
}
