{
  "spu_id": "厨房油烟机过滤棉-5c1124f9",
  "source_platform": "1688",
  "seed": {
    "keyword": "厨房油烟机过滤棉",
    "category": "清洁工具"
  },
  "keyword": "厨房油烟机过滤棉",
  "scraped_at": "2026-04-04T07:27:07.160Z",
  "candidates": [
    {
      "rank": 1,
      "title": "侧吸式厨房油烟机吸油棉接油槽隔油垫过滤棉油烟机油槽蓝色吸油棉 -",
      "source_url": "https://detail.1688.com/offer/795406018470.html",
      "prices": [
        "0",
        "¥0.9",
        "¥0.88",
        "¥0.49",
        "¥0.85"
      ],
      "attributes": {
        "brand": "无",
        "vendor_code": "ZJZY-XYM",
        "country_of_origin": "浙江",
        "color": "重量(g)",
        "material": "无纺布"
      },
      "raw_attributes": [
        {
          "key": "品牌",
          "value": "无"
        },
        {
          "key": "是否进口",
          "value": "否"
        },
        {
          "key": "货号",
          "value": "ZJZY-XYM"
        },
        {
          "key": "产地",
          "value": "浙江"
        },
        {
          "key": "箱装数量",
          "value": "200"
        },
        {
          "key": "贸易属性",
          "value": "内贸+外贸"
        },
        {
          "key": "价格段",
          "value": "5元以内"
        },
        {
          "key": "颜色",
          "value": "加厚款【10只装】"
        },
        {
          "key": "主要下游平台",
          "value": "ebay、亚马逊、wish、速卖通、独立站、LAZADA、其他"
        },
        {
          "key": "主要销售地区",
          "value": "非洲、欧洲、南美、东南亚、北美、东北亚、中东、其他"
        },
        {
          "key": "是否跨境出口专供货源",
          "value": "是"
        },
        {
          "key": "是否有专利",
          "value": "否"
        },
        {
          "key": "材质",
          "value": "无纺布"
        },
        {
          "key": "类别",
          "value": "吸油棉"
        },
        {
          "key": "货号",
          "value": "ZJZY-XYM"
        },
        {
          "key": "箱装数量",
          "value": "200"
        },
        {
          "key": "价格段",
          "value": "5元以内"
        },
        {
          "key": "主要下游平台",
          "value": "ebay,亚马逊,wish,速卖通,独立站,LAZADA,其他"
        },
        {
          "key": "是否跨境出口专供货源",
          "value": "是"
        },
        {
          "key": "颜色",
          "value": "重量(g)"
        },
        {
          "key": "加厚款【10只装】",
          "value": "65"
        }
      ],
      "images": [
        "https://cbu01.alicdn.com/img/ibank/O1CN01613zVS1pUlVdV4ajK_!!2209745415364-0-cib.jpg",
        "https://cbu01.alicdn.com/img/ibank/O1CN01NWbEoI1pUlS7aTM1b_!!2209745415364-0-cib.jpg",
        "https://cbu01.alicdn.com/img/ibank/O1CN01x4cWZ41pUlSBfWDrf_!!2209745415364-0-cib.jpg",
        "https://cbu01.alicdn.com/img/ibank/O1CN01ZxQYyM1pUlS6gp2tS_!!2209745415364-0-cib.jpg",
        "https://cbu01.alicdn.com/img/ibank/O1CN01LkCJyW1pUlS9Tmdj6_!!2209745415364-0-cib.jpg",
        "https://cbu01.alicdn.com/img/ibank/O1CN01iKinxM1pUlS9YU8L9_!!2209745415364-0-cib.jpg_sum.jpg",
        "https://cbu01.alicdn.com/img/ibank/2020/428/378/22185873824_536529798.jpg"
      ],
      "main_image": "https://cbu01.alicdn.com/img/ibank/O1CN01613zVS1pUlVdV4ajK_!!2209745415364-0-cib.jpg",
      "shop_name": "侧吸式厨房油烟机吸油棉接油槽隔油垫过滤棉油烟机油槽蓝色吸油棉无纺布｜吸油棉¥0.75100+件退货包运费先采后付回头率52%回头率52%义乌市盛箔日用品有限公司旺旺在线侧吸式厨房油烟机吸油棉接油槽隔油垫过滤棉油烟机油槽蓝色吸油棉无纺布｜吸油棉¥0.75100+件退货包运费先采后付回头率52%回头率52%义乌市盛箔日用品有限公司旺旺在线找相似"
    },
    {
      "rank": 2,
      "title": "厨房吸油油烟机过滤棉垫纸侧吸式油烟机油盒油槽吸油棉吸油毛毡 -",
      "source_url": "https://detail.1688.com/offer/757593302023.html",
      "prices": [
        "0",
        "1",
        "¥0.15",
        "0.15",
        "¥0.18"
      ],
      "attributes": {
        "vendor_code": "吸油棉",
        "country_of_origin": "浙江",
        "color": "蓝膜【10片/袋装】",
        "size": "90cm*7,90cm*10",
        "material": "无纺布"
      },
      "raw_attributes": [
        {
          "key": "是否进口",
          "value": "否"
        },
        {
          "key": "货号",
          "value": "吸油棉"
        },
        {
          "key": "产地",
          "value": "浙江"
        },
        {
          "key": "箱装数量",
          "value": "500"
        },
        {
          "key": "贸易属性",
          "value": "内贸+外贸"
        },
        {
          "key": "价格段",
          "value": "5元以内"
        },
        {
          "key": "颜色",
          "value": "蓝膜【10片/袋装】"
        },
        {
          "key": "规格",
          "value": "90cm*7、90cm*10"
        },
        {
          "key": "是否跨境出口专供货源",
          "value": "否"
        },
        {
          "key": "是否有专利",
          "value": "否"
        },
        {
          "key": "材质",
          "value": "无纺布"
        },
        {
          "key": "类别",
          "value": "吸油纸"
        },
        {
          "key": "货号",
          "value": "吸油棉"
        },
        {
          "key": "箱装数量",
          "value": "500"
        },
        {
          "key": "价格段",
          "value": "5元以内"
        },
        {
          "key": "规格",
          "value": "90cm*7,90cm*10"
        },
        {
          "key": "是否有专利",
          "value": "否"
        }
      ],
      "images": [
        "https://cbu01.alicdn.com/img/ibank/O1CN01TeJ44L1dluz8pNKeV_!!4611686018427383489-0-cbu_common_content.jpg",
        "https://cbu01.alicdn.com/img/ibank/O1CN01yklsgz1wY9eOV4U1q_!!2211366676319-0-cib.jpg",
        "https://cbu01.alicdn.com/img/ibank/O1CN01rwybCR1wY9eIFJlEl_!!2211366676319-0-cib.jpg",
        "https://cbu01.alicdn.com/img/ibank/O1CN01aES7M41wY9eQdhr09_!!2211366676319-0-cib.jpg",
        "https://cbu01.alicdn.com/img/ibank/O1CN01JrFooP1wY9mB1ydPh_!!2211366676319-0-cib.jpg_sum.jpg",
        "https://cbu01.alicdn.com/img/ibank/2020/428/378/22185873824_536529798.jpg"
      ],
      "main_image": "https://cbu01.alicdn.com/img/ibank/O1CN01TeJ44L1dluz8pNKeV_!!4611686018427383489-0-cbu_common_content.jpg",
      "shop_name": "厨房吸油油烟机过滤棉垫纸侧吸式油烟机油盒油槽吸油棉吸油毛毡无纺布｜吸油纸¥1.25退货包运费先采后付回头率48%回头率48%金华市婺宝日用品有限公司旺旺在线厨房吸油油烟机过滤棉垫纸侧吸式油烟机油盒油槽吸油棉吸油毛毡无纺布｜吸油纸¥1.25退货包运费先采后付回头率48%回头率48%金华市婺宝日用品有限公司旺旺在线找相似"
    }
  ]
}
