{
  "schema_version": "ozon-kb-v2-direct-listing",
  "generated_at": "2026-04-04T08:08:43.651Z",
  "source_platform": "1688",
  "source_url": "https://detail.1688.com/offer/952483753664.html",
  "source_platform_urls": [
    "https://detail.1688.com/offer/952483753664.html"
  ],
  "spu_id": "厨房调料瓶收纳架-转盘-06fd9e8f",
  "sku_id": "厨房调料瓶收纳架-转盘-06fd9e8f-001",
  "group_id": "厨房调料瓶收纳架-转盘-06fd9e8f",
  "variant_theme": "",
  "variant_values": {},
  "brand": "G22363",
  "model": "G22363-1",
  "vendor_code": "G22363-1",
  "barcode": "",
  "title_cn": "家用调味瓶转盘厨房油盐酱醋圆形多功能整理收纳架旋转调料置物架 -",
  "title_en": "Rotating Spice Rack Organizer, Kitchen Bottle Turntable, ABS Retro Wood Design",
  "title_ru": "Органайзер для специй кухонный вращающийся, подставка для бутылок с приправами, поворотный лоток из ABS, ретро деревянный дизайн",
  "description": "",
  "bullet_points": [
    "Вращающаяся платформа на 360° для легкого доступа ко всем бутылкам",
    "Стильный ретро-дизайн с текстурой под натуральное дерево",
    "Изготовлен из прочного и безопасного пищевого ABS-пластика",
    "Компактно организует бутылки с маслом, соусами и специями",
    "Легко чистится, устойчив к влаге и кухонным загрязнениям"
  ],
  "price": 0,
  "old_price": 0,
  "currency": "RUB",
  "stock": 0,
  "min_order_qty": 1,
  "package_quantity": 1,
  "vat": "0",
  "weight": 0.5,
  "length": 0,
  "width": 0,
  "height": 0,
  "category_path": "家居收纳",
  "category_id_source": "ai-inferred",
  "ozon_category_id": null,
  "ozon_type_id": null,
  "attributes": {
    "source_category": "家居收纳",
    "seasonality": "stable",
    "fragility": "low",
    "competition_level": "medium",
    "content_potential": "medium",
    "material": "ABS пластик",
    "color": "Ретро дерево",
    "size": "Диаметр ~25-30 см (инференция на основе изображений типовых товаров)",
    "power_supply": "",
    "country_of_origin": "CN"
  },
  "main_image": "https://cbu01.alicdn.com/img/ibank/O1CN01mnoY7N1FC9IsKCIaU_!!3524700450-0-cib.jpg",
  "images": [
    "https://cbu01.alicdn.com/img/ibank/O1CN01mnoY7N1FC9IsKCIaU_!!3524700450-0-cib.jpg",
    "https://cbu01.alicdn.com/img/ibank/O1CN01ilNMyW1FC9IqXyKG0_!!3524700450-0-cib.jpg",
    "https://cbu01.alicdn.com/img/ibank/O1CN01EXhhHR1FC9IpJaq2N_!!3524700450-0-cib.jpg",
    "https://cbu01.alicdn.com/img/ibank/O1CN010tDkFE1FC9Ir6c5ll_!!3524700450-0-cib.jpg",
    "https://cbu01.alicdn.com/img/ibank/O1CN01eXCjq11FC9Ir98j1I_!!3524700450-0-cib.jpg",
    "https://cbu01.alicdn.com/img/ibank/O1CN01wbgwFm1FC9Is320oY_!!3524700450-0-cib.jpg_sum.jpg"
  ],
  "video_url": "",
  "image_count": 6,
  "image_hash": "1e3177b0c98796e398963c2ce9308f27b6f0a33e",
  "white_background": false,
  "is_adult": false,
  "is_fragile": false,
  "dangerous_goods": false,
  "country_of_origin": "CN",
  "certificate_files": [],
  "brand_authorization": "",
  "customs_code": "",
  "restricted_category_flag": false,
  "supplier": {
    "name": "找相似揭阳市沃德百惠家居用品有限公司综合服务验厂报告采购咨询4.5退换体验4.0品质体验2.7采购咨询4.5纠纷解决4.0物流时效3.3家用调味瓶转盘厨房油盐酱醋圆形多功能整理收纳架旋转调料置物架¥27.2退货包运费先采后付回头率66%揭阳市沃德百惠家居用品有限公司旺旺在线",
    "platform": "1688",
    "shop_url": "",
    "contact": ""
  },
  "competitor_offers": [
    {
      "source_platform": "1688",
      "source_url": "https://detail.1688.com/offer/687553901750.html",
      "offer_title": "霸州市康仙庄语辉塑料制品厂",
      "shop_name": "¥7.00≥1套综合服务采购咨询4.0退换体验3.0品质体验2.0采购咨询4.0纠纷解决5.0物流时效4.1严选厨房置物架调料罐收纳整理架厨房台面多层旋转置物架子爆款¥15.5全网2.0万+件退货包运费先采后付回头率39%霸州市康仙庄语辉塑料制品厂旺旺在线",
      "shop_url": "",
      "price": 7,
      "price_text": "7",
      "currency": "CNY",
      "min_order_qty": 1,
      "main_image": "https://cbu01.alicdn.com/img/ibank/O1CN01yHDmUF1FO3WJJsetY_!!2214849940476-0-cib.jpg",
      "images": [
        "https://cbu01.alicdn.com/img/ibank/O1CN01yHDmUF1FO3WJJsetY_!!2214849940476-0-cib.jpg",
        "https://cbu01.alicdn.com/img/ibank/O1CN01jiKsWN1FO3cMQgdog_!!2214849940476-0-cib.jpg",
        "https://cbu01.alicdn.com/img/ibank/O1CN01bkVlhX1FO3cOPqtKZ_!!2214849940476-0-cib.jpg",
        "https://cbu01.alicdn.com/img/ibank/O1CN01JQiVPf1FO3cO6x54V_!!2214849940476-0-cib.jpg",
        "https://cbu01.alicdn.com/img/ibank/O1CN011lMwDI1R5zPqLR1Nu_!!6000000002061-0-cib.jpg",
        "https://cbu01.alicdn.com/img/ibank/O1CN01kgm4PK1FO3WHj1D9X_!!2214849940476-0-cib.jpg_sum.jpg",
        "https://cbu01.alicdn.com/img/ibank/O1CN01OmyPna1FO3WJDZP4M_!!2214849940476-0-cib.jpg_sum.jpg",
        "https://cbu01.alicdn.com/img/ibank/O1CN01SLCYlp1FO3WHzSBCq_!!2214849940476-0-cib.jpg_sum.jpg",
        "https://cbu01.alicdn.com/img/ibank/O1CN01PJOjAG1FO3KtZ04a5_!!2214849940476-0-cib.jpg_sum.jpg",
        "https://cbu01.alicdn.com/img/ibank/O1CN0123BG2y1FO3KsToeIK_!!2214849940476-0-cib.jpg_sum.jpg",
        "https://cbu01.alicdn.com/img/ibank/O1CN01XhJ7wa1FO3OXBEDli_!!2214849940476-0-cib.jpg_sum.jpg",
        "https://cbu01.alicdn.com/img/ibank/O1CN01UB5yn61FO3XHqTOzx_!!2214849940476-0-cib.jpg_sum.jpg",
        "https://cbu01.alicdn.com/img/ibank/2020/428/378/22185873824_536529798.jpg",
        "https://img.alicdn.com/imgextra/i4/O1CN01DkKb2925nZjxcm5pe_!!4611686018427383219-0-rate.jpg_b.jpg",
        "https://img.alicdn.com/imgextra/i3/O1CN01h64Oew25nZjwHLw4u_!!4611686018427383219-0-rate.jpg_b.jpg"
      ],
      "image_count": 15,
      "category_path": "",
      "normalizedAttributes": {
        "vendor_code": "0012",
        "country_of_origin": "其他",
        "size": "长(cm)",
        "material": "碳钢",
        "style": "现代简约风"
      },
      "weight_kg": 0,
      "page_type": "detail"
    }
  ],
  "comparison_summary": {
    "compared_at": "2026-04-04T08:08:43.651Z",
    "candidate_count": 1,
    "price_min": 7,
    "price_max": 7,
    "price_avg": 7,
    "notes": []
  },
  "data_quality": {
    "title_source": "1688-scraped",
    "description_source": "ai-inferred",
    "web_detail_valid": true,
    "inferred_fields": [
      "brand",
      "model",
      "color",
      "material",
      "size",
      "weight_kg",
      "country_of_origin",
      "vendor_code"
    ]
  },
  "analysis": {
    "product_profile": "家居收纳",
    "fragility": "low",
    "certification_risk": "low",
    "return_risk": "low",
    "competition_level": "medium",
    "content_potential": "medium",
    "seasonality": "stable",
    "target_price_rub": 0,
    "supply_price_cny": 0,
    "total_score": 0,
    "final_decision": "Review"
  },
  "ozon_api_ready": {
    "ready_for_product_import": true,
    "ready_for_price_import": false,
    "ready_for_stock_import": false,
    "offer_id": "G22363-1",
    "category_id": null,
    "type_id": null,
    "warehouse_id": null,
    "currency_code": "RUB",
    "dimensions": {
      "weight_g": 500,
      "depth_mm": 0,
      "width_mm": 0,
      "height_mm": 0
    },
    "price_payload": {
      "price": "0",
      "old_price": "0",
      "min_price": "0",
      "currency_code": "RUB"
    },
    "stock_payload": {
      "warehouse_id": null,
      "offer_id": "G22363-1",
      "stock": 0
    },
    "product_import_payload_template": {
      "offer_id": "G22363-1",
      "name": "Органайзер для специй кухонный вращающийся, подставка для бутылок с приправами, поворотный лоток из ABS, ретро деревянный дизайн",
      "description": "Этот вращающийся органайзер для специй — идеальное решение для поддержания порядка на кухне. Он позволяет компактно разместить все бутылки с маслом, уксусом, соусами и приправами, обеспечивая мгновенный доступ к нужной бутылке благодаря плавному вращению на 360 градусов. Элегантный ретро-дизайн с текстурой под дерево гармонично впишется в интерьер кухни в стиле лофт, кантри или прованс.\n\nИзготовленный из прочного и безопасного ABS-пластика, органайзер устойчив к влаге и жиру, его легко мыть. Вращающаяся конструкция экономит место на столешнице или в шкафу, делая процесс готовки более удобным и организованным. Это не просто органайзер, а стильный аксессуар для вашей кухни.",
      "barcode": "",
      "category_id": null,
      "type_id": null,
      "price": "0",
      "old_price": "0",
      "currency_code": "RUB",
      "primary_image": "https://cbu01.alicdn.com/img/ibank/O1CN01mnoY7N1FC9IsKCIaU_!!3524700450-0-cib.jpg",
      "images": [
        "https://cbu01.alicdn.com/img/ibank/O1CN01mnoY7N1FC9IsKCIaU_!!3524700450-0-cib.jpg",
        "https://cbu01.alicdn.com/img/ibank/O1CN01ilNMyW1FC9IqXyKG0_!!3524700450-0-cib.jpg",
        "https://cbu01.alicdn.com/img/ibank/O1CN01EXhhHR1FC9IpJaq2N_!!3524700450-0-cib.jpg",
        "https://cbu01.alicdn.com/img/ibank/O1CN010tDkFE1FC9Ir6c5ll_!!3524700450-0-cib.jpg",
        "https://cbu01.alicdn.com/img/ibank/O1CN01eXCjq11FC9Ir98j1I_!!3524700450-0-cib.jpg",
        "https://cbu01.alicdn.com/img/ibank/O1CN01wbgwFm1FC9Is320oY_!!3524700450-0-cib.jpg_sum.jpg"
      ],
      "dimensions": {
        "weight_g": 500,
        "depth_mm": 0,
        "width_mm": 0,
        "height_mm": 0
      },
      "attributes": [
        {
          "attribute_name": "Brand",
          "attribute_id": 85,
          "value_type": "string",
          "value": "G22363"
        },
        {
          "attribute_name": "Material",
          "attribute_id": 8229,
          "value_type": "string",
          "value": "ABS пластик"
        },
        {
          "attribute_name": "Color",
          "attribute_id": 10096,
          "value_type": "string",
          "value": "Ретро дерево"
        },
        {
          "attribute_name": "Country of origin",
          "attribute_id": 4383,
          "value_type": "string",
          "value": "CN"
        }
      ]
    },
    "listing_copy": {
      "title_ru": "Органайзер для специй кухонный вращающийся, подставка для бутылок с приправами, поворотный лоток из ABS, ретро деревянный дизайн",
      "description_ru": "Этот вращающийся органайзер для специй — идеальное решение для поддержания порядка на кухне. Он позволяет компактно разместить все бутылки с маслом, уксусом, соусами и приправами, обеспечивая мгновенный доступ к нужной бутылке благодаря плавному вращению на 360 градусов. Элегантный ретро-дизайн с текстурой под дерево гармонично впишется в интерьер кухни в стиле лофт, кантри или прованс.\n\nИзготовленный из прочного и безопасного ABS-пластика, органайзер устойчив к влаге и жиру, его легко мыть. Вращающаяся конструкция экономит место на столешнице или в шкафу, делая процесс готовки более удобным и организованным. Это не просто органайзер, а стильный аксессуар для вашей кухни.",
      "bullet_points_ru": [
        "Вращающаяся платформа на 360° для легкого доступа ко всем бутылкам",
        "Стильный ретро-дизайн с текстурой под натуральное дерево",
        "Изготовлен из прочного и безопасного пищевого ABS-пластика",
        "Компактно организует бутылки с маслом, соусами и специями",
        "Легко чистится, устойчив к влаге и кухонным загрязнениям"
      ]
    }
  },
  "seo_keywords_ru": [
    "органайзер для специй вращающийся",
    "подставка для бутылок кухонная",
    "поворотный лоток для приправ",
    "органайзер для масла и уксуса",
    "кухонный органайзер ретро"
  ]
}
