{
  "spu_id": "厨房垃圾袋挂架-39318c45",
  "source_platform": "1688",
  "seed": {
    "keyword": "厨房垃圾袋挂架",
    "category": "厨房用品"
  },
  "keyword": "厨房垃圾袋挂架",
  "scraped_at": "2026-04-04T06:25:37.727Z",
  "candidates": [
    {
      "rank": 1,
      "title": "折叠式垃圾袋挂架免打孔家用垃圾袋挂架壁挂可折叠垃圾收纳架批发 -",
      "source_url": "https://detail.1688.com/offer/891403706648.html",
      "prices": [
        "1",
        "6",
        "¥0.36",
        "0.36",
        "¥0.46"
      ],
      "attributes": {
        "material": "其他",
        "country_of_origin": "义乌",
        "compatible_models": "橱柜门卫生间厨房",
        "vendor_code": "B4358",
        "brand": "否",
        "color": "长(cm)"
      },
      "raw_attributes": [
        {
          "key": "材质",
          "value": "其他"
        },
        {
          "key": "是否进口",
          "value": "否"
        },
        {
          "key": "箱装数量",
          "value": "其他"
        },
        {
          "key": "收纳场景",
          "value": "厨房收纳,桌面收纳,卧室收纳,卫浴收纳,客厅收纳"
        },
        {
          "key": "专利",
          "value": "否"
        },
        {
          "key": "产地",
          "value": "义乌"
        },
        {
          "key": "适用范围",
          "value": "橱柜门卫生间厨房"
        },
        {
          "key": "贸易属性",
          "value": "内贸+国贸"
        },
        {
          "key": "货号",
          "value": "B4358"
        },
        {
          "key": "主要下游平台",
          "value": "ebay,亚马逊,wish,速卖通,独立站,LAZADA"
        },
        {
          "key": "有可授权的自有品牌",
          "value": "否"
        },
        {
          "key": "毛重",
          "value": "其他"
        },
        {
          "key": "颜色",
          "value": "长(cm)"
        },
        {
          "key": "折叠式垃圾架—灰色",
          "value": "19"
        },
        {
          "key": "折叠式垃圾架—白色",
          "value": "19"
        },
        {
          "key": "折叠垃圾桶【大号黄色】",
          "value": "－"
        },
        {
          "key": "折叠垃圾桶【大号紫色】",
          "value": "－"
        },
        {
          "key": "折叠垃圾桶【小号黄色】",
          "value": "－"
        },
        {
          "key": "折叠垃圾桶【小号紫色】",
          "value": "－"
        }
      ],
      "images": [
        "https://cbu01.alicdn.com/img/ibank/O1CN01giAE8B1scxSqxJ5I6_!!2206804345788-0-cib.jpg",
        "https://cbu01.alicdn.com/img/ibank/O1CN011uEj5e1scxSr0UY2i_!!2206804345788-0-cib.jpg",
        "https://cbu01.alicdn.com/img/ibank/O1CN01sBC4FK1scxSrt8pcF_!!2206804345788-0-cib.jpg",
        "https://cbu01.alicdn.com/img/ibank/O1CN01VxnVhm1scxSqZF6PR_!!2206804345788-0-cib.jpg",
        "https://cbu01.alicdn.com/img/ibank/O1CN01QWDzZE1scxSrHLlwP_!!2206804345788-0-cib.jpg",
        "https://cbu01.alicdn.com/img/ibank/O1CN01kIy98l1scxSqNdgIM_!!2206804345788-0-cib.jpg_sum.jpg",
        "https://cbu01.alicdn.com/img/ibank/O1CN01bDECLs1scxSk2dmIX_!!2206804345788-0-cib.jpg_sum.jpg",
        "https://cbu01.alicdn.com/img/ibank/O1CN01pDVboa1scxUKqt2PI_!!2206804345788-0-cib.jpg_sum.jpg",
        "https://cbu01.alicdn.com/img/ibank/O1CN01VtZNx81scxUIpf7Xb_!!2206804345788-0-cib.jpg_sum.jpg",
        "https://cbu01.alicdn.com/img/ibank/O1CN01bbLDfY1scxURBA6CB_!!2206804345788-0-cib.jpg_sum.jpg",
        "https://cbu01.alicdn.com/img/ibank/O1CN01EtUNxS1scxURDvV8N_!!2206804345788-0-cib.jpg_sum.jpg",
        "https://cbu01.alicdn.com/img/ibank/2020/428/378/22185873824_536529798.jpg",
        "https://img.alicdn.com/imgextra/i1/O1CN01QNKDBm28yW0kPl9qm_!!4611686018427385905-0-rate.jpg_b.jpg"
      ],
      "main_image": "https://cbu01.alicdn.com/img/ibank/O1CN01giAE8B1scxSqxJ5I6_!!2206804345788-0-cib.jpg",
      "shop_name": "找相似义乌市中亨日用百货有限公司综合服务验厂报告采购咨询2.5退换体验4.0品质体验3.0采购咨询2.5纠纷解决4.0物流时效3.3折叠式垃圾袋挂架免打孔家用垃圾袋挂架壁挂可折叠垃圾收纳架批发商机组货：可折叠垃圾架¥1.361.3万+件退货包运费先采后付回头率53%义乌市中亨日用百货有限公司旺旺在线"
    },
    {
      "rank": 2,
      "title": "吸盘垃圾袋支架可折叠壁挂式厨房垃圾桶挂塑料袋神器垃圾袋挂支架 -",
      "source_url": "https://detail.1688.com/offer/845992170611.html",
      "prices": [
        "10",
        "20",
        "¥6.8",
        "6.8",
        "¥17.2"
      ],
      "attributes": {
        "material": "塑料",
        "country_of_origin": "浙江",
        "compatible_models": "广泛",
        "vendor_code": "M1708",
        "color": "长(cm)"
      },
      "raw_attributes": [
        {
          "key": "材质",
          "value": "塑料"
        },
        {
          "key": "是否进口",
          "value": "否"
        },
        {
          "key": "箱装数量",
          "value": "64"
        },
        {
          "key": "收纳场景",
          "value": "厨房收纳,桌面收纳,卧室收纳,卫浴收纳,客厅收纳"
        },
        {
          "key": "专利",
          "value": "否"
        },
        {
          "key": "产地",
          "value": "浙江"
        },
        {
          "key": "适用范围",
          "value": "广泛"
        },
        {
          "key": "贸易属性",
          "value": "内销+外贸"
        },
        {
          "key": "货号",
          "value": "M1708"
        },
        {
          "key": "主要下游平台",
          "value": "ebay,亚马逊,wish,速卖通,独立站,LAZADA"
        },
        {
          "key": "是否跨境出口专供货源",
          "value": "是"
        },
        {
          "key": "颜色",
          "value": "长(cm)"
        },
        {
          "key": "透明",
          "value": "23"
        },
        {
          "key": "透黑",
          "value": "23"
        },
        {
          "key": "透明x2",
          "value": "23"
        },
        {
          "key": "透黑x2",
          "value": "23"
        },
        {
          "key": "透明+透黑",
          "value": "23"
        }
      ],
      "images": [
        "https://cbu01.alicdn.com/img/ibank/O1CN01mReAwN1JGVSpwOvC2_!!3415861001-0-cib.jpg",
        "https://cbu01.alicdn.com/img/ibank/O1CN01Dwtppp1JGVSoq3mzL_!!3415861001-0-cib.jpg",
        "https://cbu01.alicdn.com/img/ibank/O1CN017SCsQv1JGVSmAU6lp_!!3415861001-0-cib.jpg",
        "https://cbu01.alicdn.com/img/ibank/O1CN01vIdkBu1JGVSpESTHG_!!3415861001-0-cib.jpg",
        "https://cbu01.alicdn.com/img/ibank/O1CN01HnAtv81JGVSlR4tKg_!!3415861001-0-cib.jpg",
        "https://cbu01.alicdn.com/img/ibank/O1CN01YPOjIq1JGVSpwR8Yj_!!3415861001-0-cib.jpg_sum.jpg",
        "https://cbu01.alicdn.com/img/ibank/O1CN01oP6hwb1JGVSncTOgS_!!3415861001-0-cib.jpg_sum.jpg",
        "https://cbu01.alicdn.com/img/ibank/O1CN01VRdzgX1JGVSq86umo_!!3415861001-0-cib.jpg_sum.jpg",
        "https://cbu01.alicdn.com/img/ibank/O1CN01va0kwo1JGVSoHpaE2_!!3415861001-0-cib.jpg_sum.jpg",
        "https://cbu01.alicdn.com/img/ibank/O1CN01rMabxP1JGVSoHpNky_!!3415861001-0-cib.jpg_sum.jpg",
        "https://cbu01.alicdn.com/img/ibank/2020/428/378/22185873824_536529798.jpg"
      ],
      "main_image": "https://cbu01.alicdn.com/img/ibank/O1CN01mReAwN1JGVSpwOvC2_!!3415861001-0-cib.jpg",
      "shop_name": "找相似义乌市美奂供应链管理有限公司综合服务验厂报告采购咨询4.0退换体验4.0品质体验3.0采购咨询4.0纠纷解决4.0物流时效3.9吸盘垃圾袋支架可折叠壁挂式厨房垃圾桶挂塑料袋神器垃圾袋挂支架分享再减3元｜塑料垃圾架榜第17名¥10.21800+件退货包运费先采后付回头率56%义乌市美奂供应链管理有限公司旺旺在线"
    }
  ]
}
